{
    "title": "할로윈 파크 패닉! ",
    "areatype": "grid",
    "gridsize": [
        8,
        3
    ],
    "stage": [
        {
            "title": "Ev41-1",
            "name": "Ev-1",
            "grid": [
                0,
                1
            ],
            "wave": [
                {
                    "title": "wave1",
                    "enemylist": [
                        {
                            "index": "NightChickM_TU2",
                            "level": 30
                        },
                        {
                            "index": "",
                            "level": 0
                        },
                        {
                            "index": "",
                            "level": 0
                        },
                        {
                            "index": "NightChickSI_N",
                            "level": 30
                        },
                        {
                            "index": "Scout_N",
                            "level": 30
                        },
                        {
                            "index": "NightChick_TU2",
                            "level": 30
                        },
                        {
                            "index": "NightChickM_TU2",
                            "level": 30
                        },
                        {
                            "index": "",
                            "level": 0
                        },
                        {
                            "index": "",
                            "level": 0
                        }
                    ]
                },
                {
                    "title": "wave2",
                    "enemylist": [
                        {
                            "index": "",
                            "level": 0
                        },
                        {
                            "index": "Legion_N",
                            "level": 30
                        },
                        {
                            "index": "",
                            "level": 0
                        },
                        {
                            "index": "NightChickSI_N",
                            "level": 30
                        },
                        {
                            "index": "NightChickC_N",
                            "level": 30
                        },
                        {
                            "index": "Harvester_N",
                            "level": 30
                        },
                        {
                            "index": "",
                            "level": 0
                        },
                        {
                            "index": "Legion_N",
                            "level": 30
                        },
                        {
                            "index": "",
                            "level": 0
                        }
                    ]
                },
                {
                    "title": "wave3",
                    "enemylist": [
                        {
                            "index": "NightChickM_TU2",
                            "level": 31
                        },
                        {
                            "index": "NightChickC_N",
                            "level": 31
                        },
                        {
                            "index": "",
                            "level": 0
                        },
                        {
                            "index": "",
                            "level": 0
                        },
                        {
                            "index": "NightChickDE_TU2",
                            "level": 31
                        },
                        {
                            "index": "",
                            "level": 0
                        },
                        {
                            "index": "NightChickM_TU2",
                            "level": 31
                        },
                        {
                            "index": "NightChickC_N",
                            "level": 31
                        },
                        {
                            "index": "",
                            "level": 0
                        }
                    ]
                }
            ]
        },
        {
            "title": "Ev41-2",
            "prevstage": "Ev41-1",
            "name": "Ev-2",
            "grid": [
                0,
                0
            ],
            "wave": [
                {
                    "title": "wave1",
                    "enemylist": [
                        {
                            "index": "Scout_N",
                            "level": 32
                        },
                        {
                            "index": "NightChickC_N",
                            "level": 32
                        },
                        {
                            "index": "",
                            "level": 0
                        },
                        {
                            "index": "Scout_N",
                            "level": 32
                        },
                        {
                            "index": "",
                            "level": 0
                        },
                        {
                            "index": "",
                            "level": 0
                        },
                        {
                            "index": "Scout_N",
                            "level": 32
                        },
                        {
                            "index": "NightChickC_N",
                            "level": 32
                        },
                        {
                            "index": "",
                            "level": 0
                        }
                    ]
                },
                {
                    "title": "wave2",
                    "enemylist": [
                        {
                            "index": "Phalangites_TU",
                            "level": 22
                        },
                        {
                            "index": "Scout_N",
                            "level": 32
                        },
                        {
                            "index": "",
                            "level": 0
                        },
                        {
                            "index": "Scout_N",
                            "level": 32
                        },
                        {
                            "index": "",
                            "level": 0
                        },
                        {
                            "index": "",
                            "level": 0
                        },
                        {
                            "index": "Phalangites_TU",
                            "level": 20
                        },
                        {
                            "index": "Scout_N",
                            "level": 32
                        },
                        {
                            "index": "",
                            "level": 0
                        }
                    ]
                },
                {
                    "title": "wave3",
                    "enemylist": [
                        {
                            "index": "Scout_N",
                            "level": 33
                        },
                        {
                            "index": "",
                            "level": 0
                        },
                        {
                            "index": "Scout_N",
                            "level": 33
                        },
                        {
                            "index": "",
                            "level": 0
                        },
                        {
                            "index": "HeavyScout_TU",
                            "level": 33
                        },
                        {
                            "index": "",
                            "level": 0
                        },
                        {
                            "index": "Scout_N",
                            "level": 33
                        },
                        {
                            "index": "",
                            "level": 0
                        },
                        {
                            "index": "Scout_N",
                            "level": 33
                        }
                    ]
                }
            ]
        },
        {
            "title": "Ev41-3",
            "prevstage": "Ev41-2",
            "name": "Ev-3",
            "grid": [
                1,
                1
            ],
            "wave": [
                {
                    "title": "wave1",
                    "enemylist": [
                        {
                            "index": "NightChickSI_TU2",
                            "level": 34
                        },
                        {
                            "index": "NightChickC_TU3",
                            "level": 34
                        },
                        {
                            "index": "",
                            "level": 0
                        },
                        {
                            "index": "Harvester_TU3",
                            "level": 34
                        },
                        {
                            "index": "",
                            "level": 0
                        },
                        {
                            "index": "",
                            "level": 0
                        },
                        {
                            "index": "NightChickSI_TU2",
                            "level": 34
                        },
                        {
                            "index": "NightChickC_TU3",
                            "level": 34
                        },
                        {
                            "index": "",
                            "level": 0
                        }
                    ]
                },
                {
                    "title": "wave2",
                    "enemylist": [
                        {
                            "index": "",
                            "level": 0
                        },
                        {
                            "index": "NightChick_TU3",
                            "level": 34
                        },
                        {
                            "index": "Harvester_TU3",
                            "level": 34
                        },
                        {
                            "index": "Phalangites_TU",
                            "level": 26
                        },
                        {
                            "index": "",
                            "level": 0
                        },
                        {
                            "index": "",
                            "level": 0
                        },
                        {
                            "index": "",
                            "level": 0
                        },
                        {
                            "index": "NightChick_TU3",
                            "level": 34
                        },
                        {
                            "index": "Harvester_TU3",
                            "level": 34
                        }
                    ]
                },
                {
                    "title": "wave3",
                    "enemylist": [
                        {
                            "index": "",
                            "level": 0
                        },
                        {
                            "index": "Legion_N",
                            "level": 35
                        },
                        {
                            "index": "NightChickC_TU3",
                            "level": 35
                        },
                        {
                            "index": "Harvester_TU3",
                            "level": 35
                        },
                        {
                            "index": "",
                            "level": 0
                        },
                        {
                            "index": "NightChickDE_TU2",
                            "level": 35
                        },
                        {
                            "index": "",
                            "level": 0
                        },
                        {
                            "index": "Legion_N",
                            "level": 35
                        },
                        {
                            "index": "NightChickC_TU3",
                            "level": 35
                        }
                    ]
                }
            ]
        },
        {
            "title": "Ev41-4",
            "prevstage": "Ev41-3",
            "name": "Ev-4",
            "grid": [
                1,
                0
            ],
            "wave": [
                {
                    "title": "wave1",
                    "enemylist": [
                        {
                            "index": "NightChickM_TU3",
                            "level": 36
                        },
                        {
                            "index": "NightChickDE_TU2",
                            "level": 36
                        },
                        {
                            "index": "",
                            "level": 0
                        },
                        {
                            "index": "",
                            "level": 0
                        },
                        {
                            "index": "NightChickC_TU3",
                            "level": 36
                        },
                        {
                            "index": "",
                            "level": 0
                        },
                        {
                            "index": "NightChickM_TU3",
                            "level": 36
                        },
                        {
                            "index": "NightChickDE_TU2",
                            "level": 36
                        },
                        {
                            "index": "",
                            "level": 0
                        }
                    ]
                },
                {
                    "title": "wave2",
                    "enemylist": [
                        {
                            "index": "",
                            "level": 0
                        },
                        {
                            "index": "Phalangites_TU",
                            "level": 31
                        },
                        {
                            "index": "NightChickC_TU3",
                            "level": 36
                        },
                        {
                            "index": "NightChickC_TU3",
                            "level": 36
                        },
                        {
                            "index": "",
                            "level": 0
                        },
                        {
                            "index": "",
                            "level": 0
                        },
                        {
                            "index": "",
                            "level": 0
                        },
                        {
                            "index": "Phalangites_TU",
                            "level": 31
                        },
                        {
                            "index": "NightChickC_TU3",
                            "level": 36
                        }
                    ]
                },
                {
                    "title": "wave3",
                    "enemylist": [
                        {
                            "index": "",
                            "level": 0
                        },
                        {
                            "index": "NightChickC_TU3",
                            "level": 37
                        },
                        {
                            "index": "NightChickC_TU3",
                            "level": 37
                        },
                        {
                            "index": "NightChickShEx_N",
                            "level": 38
                        },
                        {
                            "index": "",
                            "level": 0
                        },
                        {
                            "index": "NightChickDE_TU2",
                            "level": 37
                        },
                        {
                            "index": "",
                            "level": 0
                        },
                        {
                            "index": "NightChickC_TU3",
                            "level": 37
                        },
                        {
                            "index": "NightChickC_TU3",
                            "level": 37
                        }
                    ]
                }
            ]
        },
        {
            "title": "Ev41-5",
            "prevstage": "Ev41-4",
            "name": "Ev-5",
            "grid": [
                2,
                1
            ],
            "wave": [
                {
                    "title": "wave1",
                    "enemylist": [
                        {
                            "index": "",
                            "level": 0
                        },
                        {
                            "index": "Legion_TU4",
                            "level": 38
                        },
                        {
                            "index": "",
                            "level": 0
                        },
                        {
                            "index": "Phalangites_TU",
                            "level": 38
                        },
                        {
                            "index": "Zapper_TU4",
                            "level": 38
                        },
                        {
                            "index": "NightChickC_TU4",
                            "level": 38
                        },
                        {
                            "index": "",
                            "level": 0
                        },
                        {
                            "index": "Legion_TU4",
                            "level": 38
                        },
                        {
                            "index": "",
                            "level": 0
                        }
                    ]
                },
                {
                    "title": "wave2",
                    "enemylist": [
                        {
                            "index": "NightChickC_TU4",
                            "level": 38
                        },
                        {
                            "index": "",
                            "level": 0
                        },
                        {
                            "index": "Zapper_TU4",
                            "level": 38
                        },
                        {
                            "index": "Phalangites_TU",
                            "level": 38
                        },
                        {
                            "index": "",
                            "level": 0
                        },
                        {
                            "index": "",
                            "level": 0
                        },
                        {
                            "index": "NightChickC_TU4",
                            "level": 38
                        },
                        {
                            "index": "",
                            "level": 0
                        },
                        {
                            "index": "Zapper_TU4",
                            "level": 38
                        }
                    ]
                },
                {
                    "title": "wave3",
                    "enemylist": [
                        {
                            "index": "NightChickDE_TU2",
                            "level": 39
                        },
                        {
                            "index": "Legion_TU4",
                            "level": 39
                        },
                        {
                            "index": "",
                            "level": 0
                        },
                        {
                            "index": "Phalangites_TU",
                            "level": 39
                        },
                        {
                            "index": "Phalangites_TU",
                            "level": 39
                        },
                        {
                            "index": "",
                            "level": 0
                        },
                        {
                            "index": "NightChickDE_TU2",
                            "level": 39
                        },
                        {
                            "index": "Legion_TU4",
                            "level": 39
                        },
                        {
                            "index": "",
                            "level": 0
                        }
                    ]
                }
            ]
        },
        {
            "title": "Ev41-6",
            "prevstage": "Ev41-5",
            "name": "Ev-6",
            "grid": [
                3,
                1
            ],
            "wave": [
                {
                    "title": "wave1",
                    "enemylist": [
                        {
                            "index": "Scout_TU4",
                            "level": 40
                        },
                        {
                            "index": "Zapper_TU4",
                            "level": 40
                        },
                        {
                            "index": "",
                            "level": 0
                        },
                        {
                            "index": "",
                            "level": 0
                        },
                        {
                            "index": "NightChickC_TU4",
                            "level": 40
                        },
                        {
                            "index": "",
                            "level": 0
                        },
                        {
                            "index": "Scout_TU4",
                            "level": 40
                        },
                        {
                            "index": "Zapper_TU4",
                            "level": 40
                        },
                        {
                            "index": "",
                            "level": 0
                        }
                    ]
                },
                {
                    "title": "wave2",
                    "enemylist": [
                        {
                            "index": "",
                            "level": 0
                        },
                        {
                            "index": "",
                            "level": 0
                        },
                        {
                            "index": "Harvester_TU4",
                            "level": 40
                        },
                        {
                            "index": "Legion_TU4",
                            "level": 40
                        },
                        {
                            "index": "NightChickDE_TU2",
                            "level": 40
                        },
                        {
                            "index": "NightChickC_TU4",
                            "level": 40
                        },
                        {
                            "index": "",
                            "level": 0
                        },
                        {
                            "index": "",
                            "level": 0
                        },
                        {
                            "index": "Harvester_TU4",
                            "level": 40
                        }
                    ]
                },
                {
                    "title": "wave3",
                    "enemylist": [
                        {
                            "index": "NightChick_TU4",
                            "level": 40
                        },
                        {
                            "index": "",
                            "level": 0
                        },
                        {
                            "index": "NightChickC_TU4",
                            "level": 40
                        },
                        {
                            "index": "Phalangites_TU",
                            "level": 40
                        },
                        {
                            "index": "",
                            "level": 0
                        },
                        {
                            "index": "Zapper_TU4",
                            "level": 40
                        },
                        {
                            "index": "NightChick_TU4",
                            "level": 40
                        },
                        {
                            "index": "",
                            "level": 0
                        },
                        {
                            "index": "NightChickC_TU4",
                            "level": 40
                        }
                    ]
                },
                {
                    "title": "wave4",
                    "enemylist": [
                        {
                            "index": "Phalangites_TU",
                            "level": 41
                        },
                        {
                            "index": "Legion_TU4",
                            "level": 41
                        },
                        {
                            "index": "",
                            "level": 0
                        },
                        {
                            "index": "",
                            "level": 0
                        },
                        {
                            "index": "NightChickDE_TU2",
                            "level": 41
                        },
                        {
                            "index": "Centurion_N",
                            "level": 42
                        },
                        {
                            "index": "Phalangites_TU",
                            "level": 41
                        },
                        {
                            "index": "Legion_TU4",
                            "level": 41
                        },
                        {
                            "index": "",
                            "level": 0
                        }
                    ]
                }
            ]
        },
        {
            "title": "Ev41-7",
            "prevstage": "Ev41-6",
            "name": "Ev-7",
            "grid": [
                3,
                0
            ],
            "wave": [
                {
                    "title": "wave1",
                    "enemylist": [
                        {
                            "index": "",
                            "level": 0
                        },
                        {
                            "index": "Wasp_N",
                            "level": 42
                        },
                        {
                            "index": "",
                            "level": 0
                        },
                        {
                            "index": "Scarab_N",
                            "level": 42
                        },
                        {
                            "index": "Scout_TU4",
                            "level": 42
                        },
                        {
                            "index": "Scout_TU4",
                            "level": 42
                        },
                        {
                            "index": "",
                            "level": 0
                        },
                        {
                            "index": "Wasp_N",
                            "level": 42
                        },
                        {
                            "index": "",
                            "level": 0
                        }
                    ]
                },
                {
                    "title": "wave2",
                    "enemylist": [
                        {
                            "index": "Wasp_N",
                            "level": 42
                        },
                        {
                            "index": "NightChickC_TU4",
                            "level": 42
                        },
                        {
                            "index": "",
                            "level": 0
                        },
                        {
                            "index": "NightChickShEx_TU2",
                            "level": 42
                        },
                        {
                            "index": "",
                            "level": 0
                        },
                        {
                            "index": "",
                            "level": 0
                        },
                        {
                            "index": "Wasp_N",
                            "level": 42
                        },
                        {
                            "index": "NightChickC_TU4",
                            "level": 42
                        },
                        {
                            "index": "",
                            "level": 0
                        }
                    ]
                },
                {
                    "title": "wave3",
                    "enemylist": [
                        {
                            "index": "",
                            "level": 0
                        },
                        {
                            "index": "NightChickC_TU4",
                            "level": 43
                        },
                        {
                            "index": "Wasp_N",
                            "level": 43
                        },
                        {
                            "index": "Wasp_N",
                            "level": 43
                        },
                        {
                            "index": "Scarab_N",
                            "level": 43
                        },
                        {
                            "index": "",
                            "level": 0
                        },
                        {
                            "index": "",
                            "level": 0
                        },
                        {
                            "index": "NightChickC_TU4",
                            "level": 43
                        },
                        {
                            "index": "Wasp_N",
                            "level": 43
                        }
                    ]
                }
            ]
        },
        {
            "title": "Ev41-8",
            "prevstage": "Ev41-7",
            "name": "Ev-8",
            "grid": [
                4,
                1
            ],
            "wave": [
                {
                    "title": "wave1",
                    "enemylist": [
                        {
                            "index": "Scout_TU4",
                            "level": 43
                        },
                        {
                            "index": "",
                            "level": 0
                        },
                        {
                            "index": "NightChickC_TU4",
                            "level": 43
                        },
                        {
                            "index": "",
                            "level": 0
                        },
                        {
                            "index": "NightChickShEx_TU2",
                            "level": 40
                        },
                        {
                            "index": "",
                            "level": 0
                        },
                        {
                            "index": "Scout_TU4",
                            "level": 43
                        },
                        {
                            "index": "",
                            "level": 0
                        },
                        {
                            "index": "NightChickC_TU4",
                            "level": 43
                        }
                    ]
                },
                {
                    "title": "wave2",
                    "enemylist": [
                        {
                            "index": "Legion_TU4",
                            "level": 43
                        },
                        {
                            "index": "NightChickC_TU4",
                            "level": 43
                        },
                        {
                            "index": "",
                            "level": 0
                        },
                        {
                            "index": "Phalangites_TU",
                            "level": 43
                        },
                        {
                            "index": "",
                            "level": 0
                        },
                        {
                            "index": "",
                            "level": 0
                        },
                        {
                            "index": "Legion_TU4",
                            "level": 43
                        },
                        {
                            "index": "NightChickC_TU4",
                            "level": 43
                        },
                        {
                            "index": "",
                            "level": 0
                        }
                    ]
                },
                {
                    "title": "wave3",
                    "enemylist": [
                        {
                            "index": "NightChickShEx_TU2",
                            "level": 44
                        },
                        {
                            "index": "NightChickC_TU4",
                            "level": 44
                        },
                        {
                            "index": "",
                            "level": 0
                        },
                        {
                            "index": "Phalangites_TU",
                            "level": 44
                        },
                        {
                            "index": "Harvester_TU4",
                            "level": 44
                        },
                        {
                            "index": "",
                            "level": 0
                        },
                        {
                            "index": "NightChickShEx_TU2",
                            "level": 44
                        },
                        {
                            "index": "NightChickC_TU4",
                            "level": 44
                        },
                        {
                            "index": "",
                            "level": 0
                        }
                    ]
                }
            ]
        },
        {
            "title": "Ev41-9",
            "prevstage": "Ev41-8",
            "name": "Ev-9",
            "grid": [
                4,
                0
            ],
            "wave": [
                {
                    "title": "wave1",
                    "enemylist": [
                        {
                            "index": "Wasp_N",
                            "level": 44
                        },
                        {
                            "index": "",
                            "level": 0
                        },
                        {
                            "index": "",
                            "level": 0
                        },
                        {
                            "index": "NightChickC_TU4",
                            "level": 44
                        },
                        {
                            "index": "Scarab_N",
                            "level": 44
                        },
                        {
                            "index": "NightChickC_TU4",
                            "level": 44
                        },
                        {
                            "index": "Wasp_N",
                            "level": 44
                        },
                        {
                            "index": "",
                            "level": 0
                        },
                        {
                            "index": "",
                            "level": 0
                        }
                    ]
                },
                {
                    "title": "wave2",
                    "enemylist": [
                        {
                            "index": "NightChick_TU4",
                            "level": 44
                        },
                        {
                            "index": "HeavyScout_TU",
                            "level": 44
                        },
                        {
                            "index": "",
                            "level": 0
                        },
                        {
                            "index": "NightChickShEx_TU2",
                            "level": 44
                        },
                        {
                            "index": "",
                            "level": 0
                        },
                        {
                            "index": "",
                            "level": 0
                        },
                        {
                            "index": "NightChick_TU4",
                            "level": 44
                        },
                        {
                            "index": "HeavyScout_TU",
                            "level": 44
                        },
                        {
                            "index": "",
                            "level": 0
                        }
                    ]
                },
                {
                    "title": "wave3",
                    "enemylist": [
                        {
                            "index": "NightChickM_TU4",
                            "level": 45
                        },
                        {
                            "index": "NightChick_TU4",
                            "level": 45
                        },
                        {
                            "index": "",
                            "level": 0
                        },
                        {
                            "index": "Phalangites_TU",
                            "level": 45
                        },
                        {
                            "index": "",
                            "level": 0
                        },
                        {
                            "index": "NightChickSP_N",
                            "level": 45
                        },
                        {
                            "index": "NightChickM_TU4",
                            "level": 45
                        },
                        {
                            "index": "NightChick_TU4",
                            "level": 45
                        },
                        {
                            "index": "",
                            "level": 0
                        }
                    ]
                }
            ]
        },
        {
            "title": "Ev41-10",
            "prevstage": "Ev41-9",
            "name": "Ev-10",
            "grid": [
                5,
                1
            ],
            "wave": [
                {
                    "title": "wave1",
                    "enemylist": [
                        {
                            "index": "Wasp_N",
                            "level": 45
                        },
                        {
                            "index": "Scout_TU4",
                            "level": 45
                        },
                        {
                            "index": "",
                            "level": 0
                        },
                        {
                            "index": "",
                            "level": 0
                        },
                        {
                            "index": "Scarab_N",
                            "level": 45
                        },
                        {
                            "index": "HeavyScout_TU",
                            "level": 45
                        },
                        {
                            "index": "Wasp_N",
                            "level": 45
                        },
                        {
                            "index": "Scout_TU4",
                            "level": 45
                        },
                        {
                            "index": "",
                            "level": 0
                        }
                    ]
                },
                {
                    "title": "wave2",
                    "enemylist": [
                        {
                            "index": "Scarab_N",
                            "level": 45
                        },
                        {
                            "index": "Wasp_N",
                            "level": 45
                        },
                        {
                            "index": "",
                            "level": 0
                        },
                        {
                            "index": "HeavyScout_TU",
                            "level": 45
                        },
                        {
                            "index": "",
                            "level": 0
                        },
                        {
                            "index": "HeavyScout_TU",
                            "level": 45
                        },
                        {
                            "index": "Scarab_N",
                            "level": 45
                        },
                        {
                            "index": "Wasp_N",
                            "level": 45
                        },
                        {
                            "index": "",
                            "level": 0
                        }
                    ]
                },
                {
                    "title": "wave3",
                    "enemylist": [
                        {
                            "index": "Scarab_N",
                            "level": 46
                        },
                        {
                            "index": "",
                            "level": 0
                        },
                        {
                            "index": "HeavyScout_TU",
                            "level": 45
                        },
                        {
                            "index": "",
                            "level": 0
                        },
                        {
                            "index": "Wasp_N",
                            "level": 45
                        },
                        {
                            "index": "Scout_TU4",
                            "level": 45
                        },
                        {
                            "index": "Scarab_N",
                            "level": 46
                        },
                        {
                            "index": "",
                            "level": 0
                        },
                        {
                            "index": "HeavyScout_TU",
                            "level": 45
                        }
                    ]
                }
            ]
        },
        {
            "title": "Ev41-11",
            "prevstage": "Ev41-10",
            "name": "Ev-11",
            "grid": [
                6,
                1
            ],
            "wave": [
                {
                    "title": "wave1",
                    "enemylist": [
                        {
                            "index": "",
                            "level": 0
                        },
                        {
                            "index": "Legion_TU4",
                            "level": 46
                        },
                        {
                            "index": "Zapper_TU4",
                            "level": 46
                        },
                        {
                            "index": "NightChickShEx_TU2",
                            "level": 46
                        },
                        {
                            "index": "NightChickDE_TU2",
                            "level": 46
                        },
                        {
                            "index": "",
                            "level": 0
                        },
                        {
                            "index": "",
                            "level": 0
                        },
                        {
                            "index": "Legion_TU4",
                            "level": 46
                        },
                        {
                            "index": "Zapper_TU4",
                            "level": 46
                        }
                    ]
                },
                {
                    "title": "wave2",
                    "enemylist": [
                        {
                            "index": "Legion_TU4",
                            "level": 46
                        },
                        {
                            "index": "",
                            "level": 0
                        },
                        {
                            "index": "NightChickSP_N",
                            "level": 46
                        },
                        {
                            "index": "Phalangites_TU",
                            "level": 46
                        },
                        {
                            "index": "NightChickShEx_TU2",
                            "level": 46
                        },
                        {
                            "index": "",
                            "level": 0
                        },
                        {
                            "index": "Legion_TU4",
                            "level": 46
                        },
                        {
                            "index": "",
                            "level": 0
                        },
                        {
                            "index": "NightChickSP_N",
                            "level": 46
                        }
                    ]
                },
                {
                    "title": "wave3",
                    "enemylist": [
                        {
                            "index": "NightChickShEx_TU2",
                            "level": 47
                        },
                        {
                            "index": "",
                            "level": 0
                        },
                        {
                            "index": "Legion_TU4",
                            "level": 47
                        },
                        {
                            "index": "",
                            "level": 0
                        },
                        {
                            "index": "Centurion_N",
                            "level": 47
                        },
                        {
                            "index": "NightChickSP_N",
                            "level": 47
                        },
                        {
                            "index": "NightChickShEx_TU2",
                            "level": 47
                        },
                        {
                            "index": "",
                            "level": 0
                        },
                        {
                            "index": "Legion_TU4",
                            "level": 47
                        }
                    ]
                }
            ]
        },
        {
            "title": "Ev41-12",
            "prevstage": "Ev41-11",
            "name": "Ev-12",
            "grid": [
                7,
                1
            ],
            "wave": [
                {
                    "title": "wave1",
                    "enemylist": [
                        {
                            "index": "NightChickM_TU4",
                            "level": 48
                        },
                        {
                            "index": "NightChickShEx_TU2",
                            "level": 48
                        },
                        {
                            "index": "",
                            "level": 0
                        },
                        {
                            "index": "",
                            "level": 0
                        },
                        {
                            "index": "NightChickDE_TU2",
                            "level": 48
                        },
                        {
                            "index": "NightChickC_TU4",
                            "level": 48
                        },
                        {
                            "index": "NightChickM_TU4",
                            "level": 48
                        },
                        {
                            "index": "NightChickShEx_TU2",
                            "level": 48
                        },
                        {
                            "index": "",
                            "level": 0
                        }
                    ]
                },
                {
                    "title": "wave2",
                    "enemylist": [
                        {
                            "index": "NightChickC_TU4",
                            "level": 48
                        },
                        {
                            "index": "NightChick_TU4",
                            "level": 48
                        },
                        {
                            "index": "",
                            "level": 0
                        },
                        {
                            "index": "BigChick_TU3",
                            "level": 48
                        },
                        {
                            "index": "",
                            "level": 0
                        },
                        {
                            "index": "NightChickDE_TU2",
                            "level": 48
                        },
                        {
                            "index": "NightChickC_TU4",
                            "level": 48
                        },
                        {
                            "index": "NightChick_TU4",
                            "level": 48
                        },
                        {
                            "index": "",
                            "level": 0
                        }
                    ]
                },
                {
                    "title": "wave3",
                    "enemylist": [
                        {
                            "index": "NightChickShEx_TU2",
                            "level": 48
                        },
                        {
                            "index": "",
                            "level": 0
                        },
                        {
                            "index": "BigChick_TU3",
                            "level": 48
                        },
                        {
                            "index": "NightChickDE_TU2",
                            "level": 48
                        },
                        {
                            "index": "",
                            "level": 0
                        },
                        {
                            "index": "NightChickC_TU4",
                            "level": 48
                        },
                        {
                            "index": "NightChickShEx_TU2",
                            "level": 48
                        },
                        {
                            "index": "",
                            "level": 0
                        },
                        {
                            "index": "BigChick_TU3",
                            "level": 48
                        }
                    ]
                },
                {
                    "title": "wave4",
                    "enemylist": [
                        {
                            "index": "BigChick_TU3",
                            "level": 48
                        },
                        {
                            "index": "NightChickC_TU4",
                            "level": 48
                        },
                        {
                            "index": "",
                            "level": 0
                        },
                        {
                            "index": "",
                            "level": 0
                        },
                        {
                            "index": "NightChickShEx_TU2",
                            "level": 48
                        },
                        {
                            "index": "FABigChick_TU4",
                            "level": 48
                        },
                        {
                            "index": "BigChick_TU3",
                            "level": 48
                        },
                        {
                            "index": "NightChickC_TU4",
                            "level": 48
                        },
                        {
                            "index": "",
                            "level": 0
                        }
                    ]
                }
            ]
        },
        {
            "title": "Ev41-13",
            "name": "Ev-1Ex",
            "grid": [
                0,
                2
            ],
            "wave": [
                {
                    "title": "wave1",
                    "enemylist": [
                        {
                            "index": "NightChickMEX_TU2",
                            "level": 48
                        },
                        {
                            "index": "",
                            "level": 0
                        },
                        {
                            "index": "NightChickEX_TU2",
                            "level": 48
                        },
                        {
                            "index": "NightChickShEx_TU2",
                            "level": 48
                        },
                        {
                            "index": "NightChickEX_TU2",
                            "level": 48
                        },
                        {
                            "index": "",
                            "level": 0
                        },
                        {
                            "index": "NightChickMEX_TU2",
                            "level": 48
                        },
                        {
                            "index": "",
                            "level": 0
                        },
                        {
                            "index": "NightChickEX_TU2",
                            "level": 48
                        }
                    ]
                },
                {
                    "title": "wave2",
                    "enemylist": [
                        {
                            "index": "",
                            "level": 0
                        },
                        {
                            "index": "NightChickCEX_TU2",
                            "level": 48
                        },
                        {
                            "index": "NightChickDE_TU3",
                            "level": 48
                        },
                        {
                            "index": "",
                            "level": 0
                        },
                        {
                            "index": "NightChickShEx_TU2",
                            "level": 48
                        },
                        {
                            "index": "NightChickEX_TU2",
                            "level": 48
                        },
                        {
                            "index": "",
                            "level": 0
                        },
                        {
                            "index": "NightChickCEX_TU2",
                            "level": 48
                        },
                        {
                            "index": "NightChickDE_TU3",
                            "level": 48
                        }
                    ]
                },
                {
                    "title": "wave3",
                    "enemylist": [
                        {
                            "index": "NightChickCEX_TU2",
                            "level": 49
                        },
                        {
                            "index": "",
                            "level": 0
                        },
                        {
                            "index": "NightChickMEX_TU2",
                            "level": 49
                        },
                        {
                            "index": "NightChickShEx_TU2",
                            "level": 49
                        },
                        {
                            "index": "",
                            "level": 0
                        },
                        {
                            "index": "NightChickCEX_TU2",
                            "level": 49
                        },
                        {
                            "index": "NightChickCEX_TU2",
                            "level": 49
                        },
                        {
                            "index": "",
                            "level": 0
                        },
                        {
                            "index": "NightChickMEX_TU2",
                            "level": 49
                        }
                    ]
                },
                {
                    "title": "wave4",
                    "enemylist": [
                        {
                            "index": "NightChickShEx_TU2",
                            "level": 50
                        },
                        {
                            "index": "NightChickCEX_TU2",
                            "level": 50
                        },
                        {
                            "index": "",
                            "level": 0
                        },
                        {
                            "index": "",
                            "level": 0
                        },
                        {
                            "index": "FABigChick_TU4",
                            "level": 51
                        },
                        {
                            "index": "NightChickCEX_TU2",
                            "level": 50
                        },
                        {
                            "index": "NightChickShEx_TU2",
                            "level": 50
                        },
                        {
                            "index": "NightChickCEX_TU2",
                            "level": 50
                        },
                        {
                            "index": "",
                            "level": 0
                        }
                    ]
                }
            ]
        },
        {
            "title": "Ev41-14",
            "prevstage": "Ev41-13",
            "name": "Ev-2Ex",
            "grid": [
                1,
                2
            ],
            "wave": [
                {
                    "title": "wave1",
                    "enemylist": [
                        {
                            "index": "ScoutEX_TU3",
                            "level": 56
                        },
                        {
                            "index": "",
                            "level": 0
                        },
                        {
                            "index": "NightChickEX_TU3",
                            "level": 56
                        },
                        {
                            "index": "NightChickShEx_TU3",
                            "level": 56
                        },
                        {
                            "index": "",
                            "level": 0
                        },
                        {
                            "index": "LegionEX_TU4",
                            "level": 41
                        },
                        {
                            "index": "ScoutEX_TU3",
                            "level": 56
                        },
                        {
                            "index": "",
                            "level": 0
                        },
                        {
                            "index": "NightChickEX_TU3",
                            "level": 56
                        }
                    ]
                },
                {
                    "title": "wave2",
                    "enemylist": [
                        {
                            "index": "",
                            "level": 0
                        },
                        {
                            "index": "LegionEX_TU4",
                            "level": 41
                        },
                        {
                            "index": "ScoutEX_TU3",
                            "level": 56
                        },
                        {
                            "index": "ScarabEX_TU2",
                            "level": 56
                        },
                        {
                            "index": "Phalangites_TU3",
                            "level": 56
                        },
                        {
                            "index": "",
                            "level": 0
                        },
                        {
                            "index": "",
                            "level": 0
                        },
                        {
                            "index": "LegionEX_TU4",
                            "level": 41
                        },
                        {
                            "index": "ScoutEX_TU3",
                            "level": 56
                        }
                    ]
                },
                {
                    "title": "wave3",
                    "enemylist": [
                        {
                            "index": "LegionEX_TU4",
                            "level": 42
                        },
                        {
                            "index": "ScoutEX_TU3",
                            "level": 57
                        },
                        {
                            "index": "",
                            "level": 0
                        },
                        {
                            "index": "",
                            "level": 0
                        },
                        {
                            "index": "ScarabEX_TU2",
                            "level": 57
                        },
                        {
                            "index": "NightChickSP_TU6",
                            "level": 56
                        },
                        {
                            "index": "LegionEX_TU4",
                            "level": 42
                        },
                        {
                            "index": "ScoutEX_TU3",
                            "level": 57
                        },
                        {
                            "index": "",
                            "level": 0
                        }
                    ]
                },
                {
                    "title": "wave4",
                    "enemylist": [
                        {
                            "index": "LegionEX_TU4",
                            "level": 44
                        },
                        {
                            "index": "",
                            "level": 0
                        },
                        {
                            "index": "NightChickSP_TU6",
                            "level": 56
                        },
                        {
                            "index": "Phalangites_TU3",
                            "level": 58
                        },
                        {
                            "index": "CenturionCF_TU2",
                            "level": 28
                        },
                        {
                            "index": "",
                            "level": 0
                        },
                        {
                            "index": "LegionEX_TU4",
                            "level": 44
                        },
                        {
                            "index": "",
                            "level": 0
                        },
                        {
                            "index": "NightChickSP_TU6",
                            "level": 56
                        }
                    ]
                }
            ]
        },
        {
            "title": "Ev41-15",
            "prevstage": "Ev41-14",
            "name": "Ev-3Ex",
            "grid": [
                2,
                2
            ],
            "wave": [
                {
                    "title": "wave1",
                    "enemylist": [
                        {
                            "index": "HeavyScout_TU4",
                            "level": 65
                        },
                        {
                            "index": "WaspEX_TU4",
                            "level": 65
                        },
                        {
                            "index": "",
                            "level": 0
                        },
                        {
                            "index": "ScarabEX_TU4",
                            "level": 65
                        },
                        {
                            "index": "",
                            "level": 0
                        },
                        {
                            "index": "ScoutEX_TU4",
                            "level": 65
                        },
                        {
                            "index": "HeavyScout_TU4",
                            "level": 65
                        },
                        {
                            "index": "WaspEX_TU4",
                            "level": 65
                        },
                        {
                            "index": "",
                            "level": 0
                        }
                    ]
                },
                {
                    "title": "wave2",
                    "enemylist": [
                        {
                            "index": "ScoutEX_TU4",
                            "level": 65
                        },
                        {
                            "index": "",
                            "level": 0
                        },
                        {
                            "index": "HeavyScout_TU4",
                            "level": 65
                        },
                        {
                            "index": "WaspEX_TU4",
                            "level": 65
                        },
                        {
                            "index": "ScarabEX_TU4",
                            "level": 65
                        },
                        {
                            "index": "",
                            "level": 0
                        },
                        {
                            "index": "ScoutEX_TU4",
                            "level": 65
                        },
                        {
                            "index": "",
                            "level": 0
                        },
                        {
                            "index": "HeavyScout_TU4",
                            "level": 65
                        }
                    ]
                },
                {
                    "title": "wave3",
                    "enemylist": [
                        {
                            "index": "",
                            "level": 0
                        },
                        {
                            "index": "WaspEX_TU4",
                            "level": 66
                        },
                        {
                            "index": "HeavyScout_TU4",
                            "level": 66
                        },
                        {
                            "index": "ScarabEX_TU4",
                            "level": 66
                        },
                        {
                            "index": "",
                            "level": 0
                        },
                        {
                            "index": "FABigChickEX_TU3",
                            "level": 67
                        },
                        {
                            "index": "",
                            "level": 0
                        },
                        {
                            "index": "WaspEX_TU4",
                            "level": 66
                        },
                        {
                            "index": "HeavyScout_TU4",
                            "level": 66
                        }
                    ]
                },
                {
                    "title": "wave4",
                    "enemylist": [
                        {
                            "index": "WaspEX_TU4",
                            "level": 67
                        },
                        {
                            "index": "",
                            "level": 0
                        },
                        {
                            "index": "HeavyScout_TU4",
                            "level": 67
                        },
                        {
                            "index": "BigChickS_TU3",
                            "level": 36
                        },
                        {
                            "index": "FABigChickEX_TU3",
                            "level": 68
                        },
                        {
                            "index": "",
                            "level": 0
                        },
                        {
                            "index": "WaspEX_TU4",
                            "level": 67
                        },
                        {
                            "index": "",
                            "level": 0
                        },
                        {
                            "index": "HeavyScout_TU4",
                            "level": 67
                        }
                    ]
                }
            ]
        },
        {
            "title": "Ev41-16",
            "prevstage": "Ev41-15",
            "name": "Ev-4Ex",
            "grid": [
                3,
                2
            ],
            "wave": [
                {
                    "title": "wave1",
                    "enemylist": [
                        {
                            "index": "ScarabEX_TU4",
                            "level": 80
                        },
                        {
                            "index": "WaspEX_TU4",
                            "level": 80
                        },
                        {
                            "index": "",
                            "level": 0
                        },
                        {
                            "index": "WaspEX_TU4",
                            "level": 80
                        },
                        {
                            "index": "",
                            "level": 0
                        },
                        {
                            "index": "LegionElite_TU2",
                            "level": 70
                        },
                        {
                            "index": "ScarabEX_TU4",
                            "level": 80
                        },
                        {
                            "index": "WaspEX_TU4",
                            "level": 80
                        },
                        {
                            "index": "",
                            "level": 0
                        }
                    ]
                },
                {
                    "title": "wave2",
                    "enemylist": [
                        {
                            "index": "WaspEX_TU4",
                            "level": 80
                        },
                        {
                            "index": "",
                            "level": 0
                        },
                        {
                            "index": "LegionElite_TU2",
                            "level": 70
                        },
                        {
                            "index": "ScarabEX_TU4",
                            "level": 80
                        },
                        {
                            "index": "",
                            "level": 0
                        },
                        {
                            "index": "NightChickDEX_TU2",
                            "level": 80
                        },
                        {
                            "index": "WaspEX_TU4",
                            "level": 80
                        },
                        {
                            "index": "",
                            "level": 0
                        },
                        {
                            "index": "LegionElite_TU2",
                            "level": 70
                        }
                    ]
                },
                {
                    "title": "wave3",
                    "enemylist": [
                        {
                            "index": "ScarabEX_TU4",
                            "level": 81
                        },
                        {
                            "index": "",
                            "level": 0
                        },
                        {
                            "index": "WaspEX_TU4",
                            "level": 81
                        },
                        {
                            "index": "",
                            "level": 0
                        },
                        {
                            "index": "NightChickDEX_TU2",
                            "level": 81
                        },
                        {
                            "index": "LegionElite_TU2",
                            "level": 71
                        },
                        {
                            "index": "ScarabEX_TU4",
                            "level": 81
                        },
                        {
                            "index": "",
                            "level": 0
                        },
                        {
                            "index": "WaspEX_TU4",
                            "level": 81
                        }
                    ]
                },
                {
                    "title": "wave4",
                    "enemylist": [
                        {
                            "index": "",
                            "level": 0
                        },
                        {
                            "index": "WaspEX_TU5",
                            "level": 82
                        },
                        {
                            "index": "Tarantula_N",
                            "level": 85
                        },
                        {
                            "index": "NightChickDEX_TU2",
                            "level": 82
                        },
                        {
                            "index": "BigChickS_TU3",
                            "level": 76
                        },
                        {
                            "index": "LegionElite_TU2",
                            "level": 75
                        },
                        {
                            "index": "",
                            "level": 0
                        },
                        {
                            "index": "WaspEX_TU5",
                            "level": 82
                        },
                        {
                            "index": "Tarantula_N",
                            "level": 85
                        }
                    ]
                }
            ]
        },
        {
            "title": "Ev41-17",
            "prevstage": "Ev41-16",
            "name": "Ev-5Ex",
            "grid": [
                4,
                2
            ],
            "wave": [
                {
                    "title": "wave1",
                    "enemylist": [
                        {
                            "index": "",
                            "level": 0
                        },
                        {
                            "index": "NightChickShEx_TU3",
                            "level": 85
                        },
                        {
                            "index": "LegionElite_TU2",
                            "level": 76
                        },
                        {
                            "index": "Testudo_TU2",
                            "level": 85
                        },
                        {
                            "index": "",
                            "level": 0
                        },
                        {
                            "index": "NightChickSP_TU9",
                            "level": 60
                        },
                        {
                            "index": "",
                            "level": 0
                        },
                        {
                            "index": "NightChickShEx_TU3",
                            "level": 85
                        },
                        {
                            "index": "LegionElite_TU2",
                            "level": 76
                        }
                    ]
                },
                {
                    "title": "wave2",
                    "enemylist": [
                        {
                            "index": "NightChickShEx_TU3",
                            "level": 85
                        },
                        {
                            "index": "LegionElite_TU2",
                            "level": 76
                        },
                        {
                            "index": "",
                            "level": 0
                        },
                        {
                            "index": "",
                            "level": 0
                        },
                        {
                            "index": "Testudo_TU2",
                            "level": 85
                        },
                        {
                            "index": "NightChickSP_TU9",
                            "level": 60
                        },
                        {
                            "index": "NightChickShEx_TU3",
                            "level": 85
                        },
                        {
                            "index": "LegionElite_TU2",
                            "level": 76
                        },
                        {
                            "index": "",
                            "level": 0
                        }
                    ]
                },
                {
                    "title": "wave3",
                    "enemylist": [
                        {
                            "index": "",
                            "level": 0
                        },
                        {
                            "index": "Testudo_TU2",
                            "level": 85
                        },
                        {
                            "index": "NightChickSP_TU9",
                            "level": 60
                        },
                        {
                            "index": "NightChickDEX_TU2",
                            "level": 85
                        },
                        {
                            "index": "",
                            "level": 0
                        },
                        {
                            "index": "LegionElite_TU2",
                            "level": 78
                        },
                        {
                            "index": "",
                            "level": 0
                        },
                        {
                            "index": "Testudo_TU2",
                            "level": 85
                        },
                        {
                            "index": "NightChickSP_TU9",
                            "level": 60
                        }
                    ]
                },
                {
                    "title": "wave4",
                    "enemylist": [
                        {
                            "index": "",
                            "level": 0
                        },
                        {
                            "index": "Tarantula_N",
                            "level": 90
                        },
                        {
                            "index": "LegionElite_TU2",
                            "level": 78
                        },
                        {
                            "index": "Testudo_TU2",
                            "level": 85
                        },
                        {
                            "index": "CenturionG_TU3",
                            "level": 30
                        },
                        {
                            "index": "NightChickDEX_TU2",
                            "level": 85
                        },
                        {
                            "index": "",
                            "level": 0
                        },
                        {
                            "index": "Tarantula_N",
                            "level": 90
                        },
                        {
                            "index": "LegionElite_TU2",
                            "level": 78
                        }
                    ]
                }
            ]
        },
        {
            "title": "Ev41-18",
            "prevstage": "Ev41-17",
            "name": "Ev-6Ex",
            "grid": [
                5,
                2
            ],
            "wave": [
                {
                    "title": "wave1",
                    "enemylist": [
                        {
                            "index": "NightChickCEX_TU5",
                            "level": 90
                        },
                        {
                            "index": "",
                            "level": 0
                        },
                        {
                            "index": "WaspEX_TU5",
                            "level": 85
                        },
                        {
                            "index": "JuggernautP_N",
                            "level": 65
                        },
                        {
                            "index": "",
                            "level": 0
                        },
                        {
                            "index": "NightChickShEx_TU4",
                            "level": 87
                        },
                        {
                            "index": "NightChickCEX_TU5",
                            "level": 90
                        },
                        {
                            "index": "",
                            "level": 0
                        },
                        {
                            "index": "WaspEX_TU5",
                            "level": 85
                        }
                    ]
                },
                {
                    "title": "wave2",
                    "enemylist": [
                        {
                            "index": "NightChickShEx_TU4",
                            "level": 87
                        },
                        {
                            "index": "WaspEX_TU5",
                            "level": 85
                        },
                        {
                            "index": "",
                            "level": 0
                        },
                        {
                            "index": "",
                            "level": 0
                        },
                        {
                            "index": "JuggernautP_N",
                            "level": 65
                        },
                        {
                            "index": "Mammoth_TU4",
                            "level": 87
                        },
                        {
                            "index": "NightChickShEx_TU4",
                            "level": 87
                        },
                        {
                            "index": "WaspEX_TU5",
                            "level": 85
                        },
                        {
                            "index": "",
                            "level": 0
                        }
                    ]
                },
                {
                    "title": "wave3",
                    "enemylist": [
                        {
                            "index": "",
                            "level": 0
                        },
                        {
                            "index": "FABigChickEX_TU4",
                            "level": 87
                        },
                        {
                            "index": "Mammoth_TU4",
                            "level": 87
                        },
                        {
                            "index": "",
                            "level": 0
                        },
                        {
                            "index": "JuggernautP_N",
                            "level": 65
                        },
                        {
                            "index": "Tarantula_TU2",
                            "level": 95
                        },
                        {
                            "index": "",
                            "level": 0
                        },
                        {
                            "index": "FABigChickEX_TU4",
                            "level": 87
                        },
                        {
                            "index": "Mammoth_TU4",
                            "level": 87
                        }
                    ]
                },
                {
                    "title": "wave4",
                    "enemylist": [
                        {
                            "index": "",
                            "level": 0
                        },
                        {
                            "index": "JuggernautP_N",
                            "level": 70
                        },
                        {
                            "index": "Tarantula_TU2",
                            "level": 95
                        },
                        {
                            "index": "NightChickCMP_EV2",
                            "level": 25
                        },
                        {
                            "index": "BigChickMG_EV2",
                            "level": 90
                        },
                        {
                            "index": "Mammoth_TU4",
                            "level": 90
                        },
                        {
                            "index": "",
                            "level": 0
                        },
                        {
                            "index": "JuggernautP_N",
                            "level": 70
                        },
                        {
                            "index": "Tarantula_TU2",
                            "level": 95
                        }
                    ]
                }
            ]
        }
    ]
}