[{"title":"해안가","loc":""},{"bg":"BG_7_8_2"},{"teller":{"image":null,"char":"나","skin":0},"text":["- 섬 전체를 진동시키던 포격 소리가 점점 잦아들고, 기쁨에 찬 병사들의 환호성이 들려오기\n시작했다."]},{"teller":{"image":null,"char":"나","skin":0},"text":["- 레오나와 마리의 분투로 네스트와의 전투는 우리의 승리로 끝났다."]},{"teller":{"image":null,"char":"BR_InvDragon","skin":0},"text":["모두가 잘 싸워 줬지만, 특히 이번 전투에서 레오나 소장이 보인 기백은 정말 대단하더군,"]},{"selection":[{"text":"레오나 말이야?","to":6}]},{"teller":{"image":null,"char":"BR_InvDragon","skin":0},"text":["일전에 당황하며 떨던 그녀가 맞는지 믿기지 않을 정도로, 정말 훌륭하게 육군을 통솔했소."]},{"teller":{"image":null,"char":"나","skin":0},"text":["- 무적의 용의 말대로, 레오나는 정말 눈부시게 전장을 지휘했다. 그 마리가 전투 도중에\n흡족한 미소를 지을 만큼 레오나는 완벽한 전술을 펼쳤다."]},{"selection":[{"text":"그래. 레오나는 노력하는 지휘관이니까.","to":9}]},{"teller":{"image":null,"char":"BR_InvDragon","skin":0},"text":["이렇게 훌륭한 지휘관들을 휘하에 두고 있다는 건, 그만큼 그대의 그릇이 크다는 뜻이겠지."]},{"teller":{"image":null,"char":"BR_InvDragon","skin":0},"text":["소관이 그대의 흠이 되지 않도록, 소관도 계속 정진하겠소,"]},{"selection":[{"text":"흠...","to":12}]},{"teller":{"image":null,"char":"나","skin":0},"text":["- 담담하게 소감을 털어놓는 무적의 용. 하지만..."]},{"teller":{"image":null,"char":"나","skin":0},"text":["- 내가 함대 포격을 조금만 더 효율적으로 사용했었더라면. 이번 전투는 훨씬 더 쉽게\n풀어낼 수 있었을지도 모른다."]},{"teller":{"image":null,"char":"BR_InvDragon","skin":0},"text":["... ..."]},{"teller":{"image":null,"char":"BR_InvDragon","skin":0},"text":["소관이 보기엔, 그대에게 뭔가 근심거리가 있는 것처럼 보이는데."]},{"teller":{"image":null,"char":"나","skin":0},"text":["- 마치 내 속을 읽고 있는 듯한 그녀의 검푸른 눈. 나는 바다로 고개를 돌린 채 생각을\n털어놓았다."]},{"selection":[{"text":"내가 좀 더 신중하게 대비해야 했어.","to":18}]},{"teller":{"image":null,"char":"BR_InvDragon","skin":0},"text":["후후. 그대의 선제 포격 지시에 문제가 될 것은 하나도 없었소이다. 그 어떤 함장이라도,\n응당 그리 대처했을 터."]},{"teller":{"image":null,"char":"BR_InvDragon","skin":0},"text":["되려, 모두가 혼란에 빠져있던 이 상황을 바로잡고 이 전투를 승리로 이끈 것은 당신의 올바른\n판단력과 유연한 지휘 덕분이 아니겠소?"]},{"teller":{"image":null,"char":"BR_InvDragon","skin":0},"text":["그걸로 모자라, 마음을 써 병사들을 마지막까지 보살피는 인품까지... 부족한 몸이지만\n소관은 진심을 다해 그대를 보좌할 것이오."]},{"selection":[{"text":"그래. 고마워.","to":22}]},{"teller":{"image":null,"char":"나","skin":0},"text":["- 무적의 용과 그녀의 함대. 점차 세력이 늘어나는만큼 내 어깨가 무거워지는게 느껴졌지만."]},{"teller":{"image":null,"char":"BR_InvDragon","skin":0},"text":["... ..."]},{"teller":{"image":null,"char":"나","skin":0},"text":["- 나를 절대적으로 믿고 따라 주는 그녀들이 있기에, 나는 절대 패배할 수 없다."]},{"comment":"스크립트 종료"}]