[{"title":"함교","loc":"그리폰의 면담 요청"},{"bg":"BG_Lobby"},{"teller":{"image":null,"char":"BR_PA00EL","skin":0},"text":["우와!!!! 이게 다 뭐야?","참치? 참치가 이렇게 많은 건 처음 봤어!"]},{"teller":{"image":null,"char":"PECS_LRL","skin":0},"text":["후. 후. 후. 어리석구나 소녀여! 한낱 식욕에 지배 당해 이성을 잃다니… ","이 고귀한 프린세스는 그런 허상 - 판타즘에는 흔들리지 않지."]},{"teller":{"image":null,"char":"BR_PA00EL","skin":0},"text":["그래? 그러시든지. 이건 내가 다 챙길 테니까…"]},{"teller":{"image":null,"char":"PECS_LRL","skin":0},"text":["어?? 무슨 소리냐? ","너의 작은 몸으로 다 들고 갈 수 있을 리 없지 않느냐?"]},{"teller":{"image":null,"char":"BR_PA00EL","skin":0},"text":["다 들고 갈 수 있거든? 요안나한테 부탁하면 되지?","참치는 도와준 사람들하고만 나눠 먹어야지~!"]},{"teller":{"image":null,"char":"PECS_LRL","skin":0},"text":["엉? 안돼! 나도, 나도 먹을 거야!","정말 너 혼자만 먹을 건 아니지? 응? 나눠 줄 거지?"]},{"teller":{"image":null,"char":"BR_PA00EL","skin":0},"text":["글쎄? 넌 고귀한 프린세스라서 관심 없지 않았냐?"]},{"teller":{"image":null,"char":"PECS_LRL","skin":0},"text":["너… 너… 그러면 에이미 부를 거야!","에이미가 네가 괴롭히면 부르랬으니까."]},{"teller":{"image":null,"char":"BR_PA00EL","skin":0},"text":["무, 무슨 소리야? 하하. 에이미 걔가 그런 말을 했을 리가…"]},{"teller":{"image":null,"char":"PECS_LRL","skin":0},"text":["에이미!!! 또 그리폰이 괴롭혀!!!!"]},{"teller":{"image":null,"char":"BR_PA00EL","skin":0},"text":["제, 젠장…"]},{"teller":{"image":null,"char":"BR_Amy","skin":0},"text":["응? 우리 공주님? 무슨 일인가요?"]},{"teller":{"image":null,"char":"PECS_LRL","skin":0},"text":["자꾸 그리폰이 놀리고… 응? 어디 갔지?"]},{"teller":{"image":null,"char":"PECS_LRL","skin":0},"text":["후후… 어리석은 미물 같으니… ","결국 이 몸이 두려워 도망을 간 모양이군."]},{"teller":{"image":null,"char":"BR_Amy","skin":0},"text":["정말… 우리 공주님, 괴롭힌다고 괴롭힘을 당해주면 안되요.","오늘 밤엔 그리폰을 더 잘 가르쳐 줘야 하겠군요."]},{"teller":{"image":null,"char":"BR_Amy","skin":0},"text":["그러지 않아도 참치를 얻어서 한껏 기분이 좋을 테니까요.","후후후."]},{"comment":"스크립트 종료"}]